infi.django_http_hooks-0.2.7-py3.7-nspkg.pth
infi/django_http_hooks/__init__.py
infi/django_http_hooks/__version__.py
infi/django_http_hooks/api.py
infi/django_http_hooks/exceptions.py
infi/django_http_hooks/http_requests.py
infi/django_http_hooks/utils.py
infi/django_http_hooks/hooks/__init__.py
infi/django_http_hooks/hooks/admin.py
infi/django_http_hooks/hooks/apps.py
infi/django_http_hooks/hooks/models.py
infi/django_http_hooks/hooks/signals.py
infi/django_http_hooks/hooks/management/__init__.py
infi/django_http_hooks/hooks/management/commands/__init__.py
infi/django_http_hooks/hooks/management/commands/delete_old_callbacks.py
infi/django_http_hooks/hooks/management/commands/monitor_callbacks.py
infi/django_http_hooks/hooks/management/commands/send_callbacks.py
infi/django_http_hooks/hooks/migrations/0001_initial.py
infi/django_http_hooks/hooks/migrations/0002_create_signals.py
infi/django_http_hooks/hooks/migrations/__init__.py
infi/django_http_hooks/tests/__init__.py
infi/django_http_hooks/tests/wsgi_server.py
infi/django_http_hooks/tests/demo_project/__init__.py
infi/django_http_hooks/tests/demo_project/manage.py
infi/django_http_hooks/tests/demo_project/demo_app/__init__.py
infi/django_http_hooks/tests/demo_project/demo_app/apps.py
infi/django_http_hooks/tests/demo_project/demo_app/models.py
infi/django_http_hooks/tests/demo_project/demo_app/migrations/0001_initial.py
infi/django_http_hooks/tests/demo_project/demo_app/migrations/__init__.py
infi/django_http_hooks/tests/demo_project/demo_project/__init__.py
infi/django_http_hooks/tests/demo_project/demo_project/settings.py
infi/django_http_hooks/tests/demo_project/demo_project/test_signals.py
infi/django_http_hooks/tests/demo_project/demo_project/urls.py
infi/django_http_hooks/tests/demo_project/demo_project/wsgi.py
infi.django_http_hooks-0.2.7.dist-info/LICENSE
infi.django_http_hooks-0.2.7.dist-info/METADATA
infi.django_http_hooks-0.2.7.dist-info/WHEEL
infi.django_http_hooks-0.2.7.dist-info/entry_points.txt
infi.django_http_hooks-0.2.7.dist-info/namespace_packages.txt
infi.django_http_hooks-0.2.7.dist-info/top_level.txt
infi.django_http_hooks-0.2.7.dist-info/RECORD
